{"info":{"file":"src/App.js","fileShort":"App.js","fileSafe":"App_js","link":"files/App_js/index.html"},"complexity":{"methodAggregate":{"cyclomatic":1,"cyclomaticDensity":5,"halstead":{"bugs":0.47,"difficulty":13.721,"effort":19360.999,"length":219,"time":1075.611,"vocabulary":87,"volume":1411.005,"operands":{"distinct":70,"total":113,"identifiers":["__stripped__"]},"operators":{"distinct":17,"total":106,"identifiers":["__stripped__"]}},"params":5,"sloc":{"logical":20,"physical":206}},"settings":{"commonjs":false,"forin":false,"logicalor":true,"switchcase":true,"trycatch":false,"newmi":true},"classes":[{"methodAggregate":{"cyclomatic":1,"cyclomaticDensity":33.333,"halstead":{"bugs":0.017,"difficulty":4.8,"effort":249.079,"length":15,"time":13.838,"vocabulary":11,"volume":51.891,"operands":{"distinct":5,"total":8,"identifiers":["__stripped__"]},"operators":{"distinct":6,"total":7,"identifiers":["__stripped__"]}},"params":2,"sloc":{"logical":3,"physical":10}},"errors":[],"lineEnd":59,"lineStart":50,"methods":[{"cyclomatic":1,"cyclomaticDensity":100,"halstead":{"bugs":0.002,"difficulty":1,"effort":4.755,"length":3,"time":0.264,"vocabulary":3,"volume":4.755,"operands":{"distinct":1,"total":1,"identifiers":["__stripped__"]},"operators":{"distinct":2,"total":2,"identifiers":["__stripped__"]}},"params":1,"sloc":{"logical":1,"physical":8},"errors":[],"lineEnd":58,"lineStart":51,"name":"constructor","complexity":{"cyclomatic":1,"sloc":{"logical":1,"physical":8},"halstead":{"bugs":0.002,"difficulty":1,"effort":4.755,"length":3,"time":0.264,"vocabulary":3,"volume":4.755,"operands":{"distinct":1,"total":1,"identifiers":["__stripped__"]},"operators":{"distinct":2,"total":2,"identifiers":["__stripped__"]}}},"line":51},{"cyclomatic":1,"cyclomaticDensity":50,"halstead":{"bugs":0.008,"difficulty":3.333,"effort":84.221,"length":9,"time":4.679,"vocabulary":7,"volume":25.266,"operands":{"distinct":3,"total":5,"identifiers":["__stripped__"]},"operators":{"distinct":4,"total":4,"identifiers":["__stripped__"]}},"params":1,"sloc":{"logical":2,"physical":6},"errors":[],"lineEnd":57,"lineStart":52,"name":"<anonymous>","complexity":{"cyclomatic":1,"sloc":{"logical":2,"physical":6},"halstead":{"bugs":0.008,"difficulty":3.333,"effort":84.221,"length":9,"time":4.679,"vocabulary":7,"volume":25.266,"operands":{"distinct":3,"total":5,"identifiers":["__stripped__"]},"operators":{"distinct":4,"total":4,"identifiers":["__stripped__"]}}},"line":52}],"methodAverage":{"cyclomatic":1,"cyclomaticDensity":75,"halstead":{"bugs":0.005,"difficulty":2.167,"effort":44.488,"length":6,"time":2.472,"vocabulary":5,"volume":15.011,"operands":{"distinct":2,"total":3},"operators":{"distinct":3,"total":3}},"params":1,"sloc":{"logical":1.5,"physical":7}},"name":"Concept","maintainability":88.568}],"dependencies":[{"line":19,"path":"./App.scss","type":"esm"},{"line":20,"path":"react","type":"esm"},{"line":22,"path":"./interfaces/WPHeader","type":"esm"},{"line":23,"path":"./interfaces/WPFooter","type":"esm"},{"line":24,"path":"./interface.parts/Button","type":"esm"},{"line":25,"path":"./infrastructure/services","type":"esm"},{"line":26,"path":"./interface.parts/List","type":"esm"},{"line":27,"path":"./interfaces/WPLocation","type":"esm"},{"line":28,"path":"./interfaces/WPWeather","type":"esm"},{"line":29,"path":"./assets/interface-scripts/link","type":"esm"},{"line":30,"path":"./interface.parts/Link","type":"esm"}],"errors":[],"lineEnd":206,"lineStart":1,"maintainability":87.965,"methods":[{"cyclomatic":1,"cyclomaticDensity":100,"halstead":{"bugs":0.005,"difficulty":1.333,"effort":18.575,"length":6,"time":1.032,"vocabulary":5,"volume":13.932,"operands":{"distinct":3,"total":4,"identifiers":["__stripped__"]},"operators":{"distinct":2,"total":2,"identifiers":["__stripped__"]}},"params":1,"sloc":{"logical":1,"physical":3},"errors":[],"lineEnd":69,"lineStart":67,"name":"<anonymous>","complexity":{"cyclomatic":1,"sloc":{"logical":1,"physical":3},"halstead":{"bugs":0.005,"difficulty":1.333,"effort":18.575,"length":6,"time":1.032,"vocabulary":5,"volume":13.932,"operands":{"distinct":3,"total":4,"identifiers":["__stripped__"]},"operators":{"distinct":2,"total":2,"identifiers":["__stripped__"]}}},"line":67},{"cyclomatic":1,"cyclomaticDensity":14.286,"halstead":{"bugs":0.117,"difficulty":5.231,"effort":1836.183,"length":69,"time":102.01,"vocabulary":34,"volume":351.035,"operands":{"distinct":26,"total":34,"identifiers":["__stripped__"]},"operators":{"distinct":8,"total":35,"identifiers":["__stripped__"]}},"params":0,"sloc":{"logical":7,"physical":127},"errors":[],"lineEnd":201,"lineStart":75,"name":"App","complexity":{"cyclomatic":1,"sloc":{"logical":7,"physical":127},"halstead":{"bugs":0.117,"difficulty":5.231,"effort":1836.183,"length":69,"time":102.01,"vocabulary":34,"volume":351.035,"operands":{"distinct":26,"total":34,"identifiers":["__stripped__"]},"operators":{"distinct":8,"total":35,"identifiers":["__stripped__"]}}},"line":75},{"cyclomatic":1,"cyclomaticDensity":100,"halstead":{"bugs":0.004,"difficulty":1,"effort":11.61,"length":5,"time":0.645,"vocabulary":5,"volume":11.61,"operands":{"distinct":3,"total":3,"identifiers":["__stripped__"]},"operators":{"distinct":2,"total":2,"identifiers":["__stripped__"]}},"params":0,"sloc":{"logical":1,"physical":3},"errors":[],"lineEnd":114,"lineStart":112,"name":"<anonymous>","complexity":{"cyclomatic":1,"sloc":{"logical":1,"physical":3},"halstead":{"bugs":0.004,"difficulty":1,"effort":11.61,"length":5,"time":0.645,"vocabulary":5,"volume":11.61,"operands":{"distinct":3,"total":3,"identifiers":["__stripped__"]},"operators":{"distinct":2,"total":2,"identifiers":["__stripped__"]}}},"line":112},{"cyclomatic":1,"cyclomaticDensity":100,"halstead":{"bugs":0.003,"difficulty":0.5,"effort":4,"length":4,"time":0.222,"vocabulary":4,"volume":8,"operands":{"distinct":3,"total":3,"identifiers":["__stripped__"]},"operators":{"distinct":1,"total":1,"identifiers":["__stripped__"]}},"params":1,"sloc":{"logical":1,"physical":8},"errors":[],"lineEnd":128,"lineStart":121,"name":"<anonymous>","complexity":{"cyclomatic":1,"sloc":{"logical":1,"physical":8},"halstead":{"bugs":0.003,"difficulty":0.5,"effort":4,"length":4,"time":0.222,"vocabulary":4,"volume":8,"operands":{"distinct":3,"total":3,"identifiers":["__stripped__"]},"operators":{"distinct":1,"total":1,"identifiers":["__stripped__"]}}},"line":121},{"cyclomatic":1,"cyclomaticDensity":0,"halstead":{"bugs":0.007,"difficulty":1.25,"effort":25.85,"length":8,"time":1.436,"vocabulary":6,"volume":20.68,"operands":{"distinct":4,"total":5,"identifiers":["__stripped__"]},"operators":{"distinct":2,"total":3,"identifiers":["__stripped__"]}},"params":1,"sloc":{"logical":0,"physical":1},"errors":[],"lineEnd":160,"lineStart":160,"name":"<anonymous>","complexity":{"cyclomatic":1,"sloc":{"logical":0,"physical":1},"halstead":{"bugs":0.007,"difficulty":1.25,"effort":25.85,"length":8,"time":1.436,"vocabulary":6,"volume":20.68,"operands":{"distinct":4,"total":5,"identifiers":["__stripped__"]},"operators":{"distinct":2,"total":3,"identifiers":["__stripped__"]}}},"line":160},{"cyclomatic":1,"cyclomaticDensity":0,"halstead":{"bugs":0.005,"difficulty":1,"effort":15.51,"length":6,"time":0.862,"vocabulary":6,"volume":15.51,"operands":{"distinct":4,"total":4,"identifiers":["__stripped__"]},"operators":{"distinct":2,"total":2,"identifiers":["__stripped__"]}},"params":0,"sloc":{"logical":0,"physical":1},"errors":[],"lineEnd":178,"lineStart":178,"name":"<anonymous>","complexity":{"cyclomatic":1,"sloc":{"logical":0,"physical":1},"halstead":{"bugs":0.005,"difficulty":1,"effort":15.51,"length":6,"time":0.862,"vocabulary":6,"volume":15.51,"operands":{"distinct":4,"total":4,"identifiers":["__stripped__"]},"operators":{"distinct":2,"total":2,"identifiers":["__stripped__"]}}},"line":178},{"cyclomatic":1,"cyclomaticDensity":0,"halstead":{"bugs":0.005,"difficulty":1,"effort":15.51,"length":6,"time":0.862,"vocabulary":6,"volume":15.51,"operands":{"distinct":4,"total":4,"identifiers":["__stripped__"]},"operators":{"distinct":2,"total":2,"identifiers":["__stripped__"]}},"params":0,"sloc":{"logical":0,"physical":1},"errors":[],"lineEnd":179,"lineStart":179,"name":"<anonymous>","complexity":{"cyclomatic":1,"sloc":{"logical":0,"physical":1},"halstead":{"bugs":0.005,"difficulty":1,"effort":15.51,"length":6,"time":0.862,"vocabulary":6,"volume":15.51,"operands":{"distinct":4,"total":4,"identifiers":["__stripped__"]},"operators":{"distinct":2,"total":2,"identifiers":["__stripped__"]}}},"line":179},{"cyclomatic":1,"cyclomaticDensity":0,"halstead":{"bugs":0.005,"difficulty":1,"effort":15.51,"length":6,"time":0.862,"vocabulary":6,"volume":15.51,"operands":{"distinct":4,"total":4,"identifiers":["__stripped__"]},"operators":{"distinct":2,"total":2,"identifiers":["__stripped__"]}},"params":0,"sloc":{"logical":0,"physical":1},"errors":[],"lineEnd":185,"lineStart":185,"name":"<anonymous>","complexity":{"cyclomatic":1,"sloc":{"logical":0,"physical":1},"halstead":{"bugs":0.005,"difficulty":1,"effort":15.51,"length":6,"time":0.862,"vocabulary":6,"volume":15.51,"operands":{"distinct":4,"total":4,"identifiers":["__stripped__"]},"operators":{"distinct":2,"total":2,"identifiers":["__stripped__"]}}},"line":185},{"cyclomatic":1,"cyclomaticDensity":0,"halstead":{"bugs":0.005,"difficulty":1,"effort":15.51,"length":6,"time":0.862,"vocabulary":6,"volume":15.51,"operands":{"distinct":4,"total":4,"identifiers":["__stripped__"]},"operators":{"distinct":2,"total":2,"identifiers":["__stripped__"]}},"params":0,"sloc":{"logical":0,"physical":1},"errors":[],"lineEnd":191,"lineStart":191,"name":"<anonymous>","complexity":{"cyclomatic":1,"sloc":{"logical":0,"physical":1},"halstead":{"bugs":0.005,"difficulty":1,"effort":15.51,"length":6,"time":0.862,"vocabulary":6,"volume":15.51,"operands":{"distinct":4,"total":4,"identifiers":["__stripped__"]},"operators":{"distinct":2,"total":2,"identifiers":["__stripped__"]}}},"line":191}],"methodAverage":{"cyclomatic":1,"cyclomaticDensity":42.208,"halstead":{"bugs":0.015,"difficulty":1.604,"effort":186.112,"length":11.636,"time":10.34,"vocabulary":8,"volume":45.211,"operands":{"distinct":5.364,"total":6.455},"operators":{"distinct":2.636,"total":5.182}},"params":0.455,"sloc":{"logical":1.182,"physical":14.545}},"module":"App.js","aggregate":{"complexity":{"cyclomatic":1,"cyclomaticDensity":5,"halstead":{"bugs":0.47,"difficulty":13.721,"effort":19360.999,"length":219,"time":1075.611,"vocabulary":87,"volume":1411.005,"operands":{"distinct":70,"total":113,"identifiers":["__stripped__"]},"operators":{"distinct":17,"total":106,"identifiers":["__stripped__"]}},"params":5,"sloc":{"logical":20,"physical":206}}},"functions":[{"cyclomatic":1,"cyclomaticDensity":100,"halstead":{"bugs":0.005,"difficulty":1.333,"effort":18.575,"length":6,"time":1.032,"vocabulary":5,"volume":13.932,"operands":{"distinct":3,"total":4,"identifiers":["__stripped__"]},"operators":{"distinct":2,"total":2,"identifiers":["__stripped__"]}},"params":1,"sloc":{"logical":1,"physical":3},"errors":[],"lineEnd":69,"lineStart":67,"name":"<anonymous>","complexity":{"cyclomatic":1,"sloc":{"logical":1,"physical":3},"halstead":{"bugs":0.005,"difficulty":1.333,"effort":18.575,"length":6,"time":1.032,"vocabulary":5,"volume":13.932,"operands":{"distinct":3,"total":4,"identifiers":["__stripped__"]},"operators":{"distinct":2,"total":2,"identifiers":["__stripped__"]}}},"line":67},{"cyclomatic":1,"cyclomaticDensity":14.286,"halstead":{"bugs":0.117,"difficulty":5.231,"effort":1836.183,"length":69,"time":102.01,"vocabulary":34,"volume":351.035,"operands":{"distinct":26,"total":34,"identifiers":["__stripped__"]},"operators":{"distinct":8,"total":35,"identifiers":["__stripped__"]}},"params":0,"sloc":{"logical":7,"physical":127},"errors":[],"lineEnd":201,"lineStart":75,"name":"App","complexity":{"cyclomatic":1,"sloc":{"logical":7,"physical":127},"halstead":{"bugs":0.117,"difficulty":5.231,"effort":1836.183,"length":69,"time":102.01,"vocabulary":34,"volume":351.035,"operands":{"distinct":26,"total":34,"identifiers":["__stripped__"]},"operators":{"distinct":8,"total":35,"identifiers":["__stripped__"]}}},"line":75},{"cyclomatic":1,"cyclomaticDensity":100,"halstead":{"bugs":0.004,"difficulty":1,"effort":11.61,"length":5,"time":0.645,"vocabulary":5,"volume":11.61,"operands":{"distinct":3,"total":3,"identifiers":["__stripped__"]},"operators":{"distinct":2,"total":2,"identifiers":["__stripped__"]}},"params":0,"sloc":{"logical":1,"physical":3},"errors":[],"lineEnd":114,"lineStart":112,"name":"<anonymous>","complexity":{"cyclomatic":1,"sloc":{"logical":1,"physical":3},"halstead":{"bugs":0.004,"difficulty":1,"effort":11.61,"length":5,"time":0.645,"vocabulary":5,"volume":11.61,"operands":{"distinct":3,"total":3,"identifiers":["__stripped__"]},"operators":{"distinct":2,"total":2,"identifiers":["__stripped__"]}}},"line":112},{"cyclomatic":1,"cyclomaticDensity":100,"halstead":{"bugs":0.003,"difficulty":0.5,"effort":4,"length":4,"time":0.222,"vocabulary":4,"volume":8,"operands":{"distinct":3,"total":3,"identifiers":["__stripped__"]},"operators":{"distinct":1,"total":1,"identifiers":["__stripped__"]}},"params":1,"sloc":{"logical":1,"physical":8},"errors":[],"lineEnd":128,"lineStart":121,"name":"<anonymous>","complexity":{"cyclomatic":1,"sloc":{"logical":1,"physical":8},"halstead":{"bugs":0.003,"difficulty":0.5,"effort":4,"length":4,"time":0.222,"vocabulary":4,"volume":8,"operands":{"distinct":3,"total":3,"identifiers":["__stripped__"]},"operators":{"distinct":1,"total":1,"identifiers":["__stripped__"]}}},"line":121},{"cyclomatic":1,"cyclomaticDensity":0,"halstead":{"bugs":0.007,"difficulty":1.25,"effort":25.85,"length":8,"time":1.436,"vocabulary":6,"volume":20.68,"operands":{"distinct":4,"total":5,"identifiers":["__stripped__"]},"operators":{"distinct":2,"total":3,"identifiers":["__stripped__"]}},"params":1,"sloc":{"logical":0,"physical":1},"errors":[],"lineEnd":160,"lineStart":160,"name":"<anonymous>","complexity":{"cyclomatic":1,"sloc":{"logical":0,"physical":1},"halstead":{"bugs":0.007,"difficulty":1.25,"effort":25.85,"length":8,"time":1.436,"vocabulary":6,"volume":20.68,"operands":{"distinct":4,"total":5,"identifiers":["__stripped__"]},"operators":{"distinct":2,"total":3,"identifiers":["__stripped__"]}}},"line":160},{"cyclomatic":1,"cyclomaticDensity":0,"halstead":{"bugs":0.005,"difficulty":1,"effort":15.51,"length":6,"time":0.862,"vocabulary":6,"volume":15.51,"operands":{"distinct":4,"total":4,"identifiers":["__stripped__"]},"operators":{"distinct":2,"total":2,"identifiers":["__stripped__"]}},"params":0,"sloc":{"logical":0,"physical":1},"errors":[],"lineEnd":178,"lineStart":178,"name":"<anonymous>","complexity":{"cyclomatic":1,"sloc":{"logical":0,"physical":1},"halstead":{"bugs":0.005,"difficulty":1,"effort":15.51,"length":6,"time":0.862,"vocabulary":6,"volume":15.51,"operands":{"distinct":4,"total":4,"identifiers":["__stripped__"]},"operators":{"distinct":2,"total":2,"identifiers":["__stripped__"]}}},"line":178},{"cyclomatic":1,"cyclomaticDensity":0,"halstead":{"bugs":0.005,"difficulty":1,"effort":15.51,"length":6,"time":0.862,"vocabulary":6,"volume":15.51,"operands":{"distinct":4,"total":4,"identifiers":["__stripped__"]},"operators":{"distinct":2,"total":2,"identifiers":["__stripped__"]}},"params":0,"sloc":{"logical":0,"physical":1},"errors":[],"lineEnd":179,"lineStart":179,"name":"<anonymous>","complexity":{"cyclomatic":1,"sloc":{"logical":0,"physical":1},"halstead":{"bugs":0.005,"difficulty":1,"effort":15.51,"length":6,"time":0.862,"vocabulary":6,"volume":15.51,"operands":{"distinct":4,"total":4,"identifiers":["__stripped__"]},"operators":{"distinct":2,"total":2,"identifiers":["__stripped__"]}}},"line":179},{"cyclomatic":1,"cyclomaticDensity":0,"halstead":{"bugs":0.005,"difficulty":1,"effort":15.51,"length":6,"time":0.862,"vocabulary":6,"volume":15.51,"operands":{"distinct":4,"total":4,"identifiers":["__stripped__"]},"operators":{"distinct":2,"total":2,"identifiers":["__stripped__"]}},"params":0,"sloc":{"logical":0,"physical":1},"errors":[],"lineEnd":185,"lineStart":185,"name":"<anonymous>","complexity":{"cyclomatic":1,"sloc":{"logical":0,"physical":1},"halstead":{"bugs":0.005,"difficulty":1,"effort":15.51,"length":6,"time":0.862,"vocabulary":6,"volume":15.51,"operands":{"distinct":4,"total":4,"identifiers":["__stripped__"]},"operators":{"distinct":2,"total":2,"identifiers":["__stripped__"]}}},"line":185},{"cyclomatic":1,"cyclomaticDensity":0,"halstead":{"bugs":0.005,"difficulty":1,"effort":15.51,"length":6,"time":0.862,"vocabulary":6,"volume":15.51,"operands":{"distinct":4,"total":4,"identifiers":["__stripped__"]},"operators":{"distinct":2,"total":2,"identifiers":["__stripped__"]}},"params":0,"sloc":{"logical":0,"physical":1},"errors":[],"lineEnd":191,"lineStart":191,"name":"<anonymous>","complexity":{"cyclomatic":1,"sloc":{"logical":0,"physical":1},"halstead":{"bugs":0.005,"difficulty":1,"effort":15.51,"length":6,"time":0.862,"vocabulary":6,"volume":15.51,"operands":{"distinct":4,"total":4,"identifiers":["__stripped__"]},"operators":{"distinct":2,"total":2,"identifiers":["__stripped__"]}}},"line":191},{"cyclomatic":1,"cyclomaticDensity":100,"halstead":{"bugs":0.002,"difficulty":1,"effort":4.755,"length":3,"time":0.264,"vocabulary":3,"volume":4.755,"operands":{"distinct":1,"total":1,"identifiers":["__stripped__"]},"operators":{"distinct":2,"total":2,"identifiers":["__stripped__"]}},"params":1,"sloc":{"logical":1,"physical":8},"errors":[],"lineEnd":58,"lineStart":51,"name":"constructor","complexity":{"cyclomatic":1,"sloc":{"logical":1,"physical":8},"halstead":{"bugs":0.002,"difficulty":1,"effort":4.755,"length":3,"time":0.264,"vocabulary":3,"volume":4.755,"operands":{"distinct":1,"total":1,"identifiers":["__stripped__"]},"operators":{"distinct":2,"total":2,"identifiers":["__stripped__"]}}},"line":51},{"cyclomatic":1,"cyclomaticDensity":50,"halstead":{"bugs":0.008,"difficulty":3.333,"effort":84.221,"length":9,"time":4.679,"vocabulary":7,"volume":25.266,"operands":{"distinct":3,"total":5,"identifiers":["__stripped__"]},"operators":{"distinct":4,"total":4,"identifiers":["__stripped__"]}},"params":1,"sloc":{"logical":2,"physical":6},"errors":[],"lineEnd":57,"lineStart":52,"name":"<anonymous>","complexity":{"cyclomatic":1,"sloc":{"logical":2,"physical":6},"halstead":{"bugs":0.008,"difficulty":3.333,"effort":84.221,"length":9,"time":4.679,"vocabulary":7,"volume":25.266,"operands":{"distinct":3,"total":5,"identifiers":["__stripped__"]},"operators":{"distinct":4,"total":4,"identifiers":["__stripped__"]}}},"line":52}]},"eslint":{"messages":[{"severity":"warn","line":20,"column":10,"message":"'FC' is defined but never used.","fix":{}},{"severity":"warn","line":29,"column":8,"message":"'link' is defined but never used.","fix":{}},{"severity":"warn","line":30,"column":8,"message":"'Link' is defined but never used.","fix":{}}]}}